Workbook

Sheet Sheet3
A3: Sum of Price | B3: Column Labels
A4: Row Labels | B4: West | C4: Grand Total
A5: Berniece Blakely | B5: 12125 | C5: 12125
A6: Lily Weatherford | B6: 9612 | C6: 9612
A7: Natividad Grandberry | B7: 9044 | C7: 9044
A8: Kazuko Serrato | B8: 8865 | C8: 8865
A9: Caryn Conry | B9: 7981 | C9: 7981
A10: Fe Finchum | B10: 7602 | C10: 7602
A11: Linn Muncy | B11: 7168 | C11: 7168
A12: Cecelia Beeler | B12: 7049 | C12: 7049
A13: Dung Do | B13: 6848 | C13: 6848
A14: Kyla Danek | B14: 6614 | C14: 6614
A15: Nana Nolette | B15: 6071 | C15: 6071
A16: Katharine Pearcy | B16: 5326 | C16: 5326
... A36: Grand Total | B36: 153178 | C36: 153178

Sheet CUSTOMER
A1: Customer_ID | B1: Customer_Name | C1: Customer_Email | D1: City_ID | E1: Customer_Zipcode | F1: Latitude | G1: Longitude | H1: Region | I1: Price
A2: 1 | B2: Agatha Clauss | C2: a.clauss@gmail.com | D2: 35 | E2: 75016 | F2: 32.76726 | G2: -96.77762 | H2: =_xlfn.XLOOKUP(Table1[[#This Row],[City_ID]],CITY!$A$2:$A$39,CITY!$D$2:$D$39) -> South | I2: 3921
A3: 2 | B3: Alaine Kindig | C3: a.kindig@hotmail.com | D3: 7 | E3: 94105 | F3: 37.78922 | G3: -122.3957 | H3: =_xlfn.XLOOKUP(Table1[[#This Row],[City_ID]],CITY!$A$2:$A$39,CITY!$D$2:$D$39) -> West | I3: 3191
A4: 3 | B4: Alonzo Stoltz | C4: a.stoltz@yahoo.com | D4: 17 | E4: 33701 | F4: 27.77095 | G4: -82.63931 | H4: =_xlfn.XLOOKUP(Table1[[#This Row],[City_ID]],CITY!$A$2:$A$39,CITY!$D$2:$D$39) -> South | I4: 4030
A5: 4 | B5: Andreas Armour | C5: a.armour@outlook.com | D5: 30 | E5: 10001 | F5: 40.75074 | G5: -73.99653 | H5: =_xlfn.XLOOKUP(Table1[[#This Row],[City_ID]],CITY!$A$2:$A$39,CITY!$D$2:$D$39) -> MidAtlantic | I5: 7313
A6: 5 | B6: Anette Abdulla | C6: a.abdulla@aol.com | D6: 10 | E6: 6106 | F6: 41.7469 | G6: -72.69593 | H6: =_xlfn.XLOOKUP(Table1[[#This Row],[City_ID]],CITY!$A$2:$A$39,CITY!$D$2:$D$39) -> NorthEast | I6: 1152
A7: 6 | B7: Anjelica Usrey | C7: a.usrey@mail.com | D7: 23 | E7: 8404 | F7: 39.5092 | G7: -74.60855 | H7: =_xlfn.XLOOKUP(Table1[[#This Row],[City_ID]],CITY!$A$2:$A$39,CITY!$D$2:$D$39) -> MidAtlantic | I7: 775
A8: 7 | B8: Ardath Peaslee | C8: a.peaslee@gmail.com | D8: 13 | E8: 6095 | F8: 41.8573 | G8: -72.66654 | H8: =_xlfn.XLOOKUP(Table1[[#This Row],[City_ID]],CITY!$A$2:$A$39,CITY!$D$2:$D$39) -> NorthEast | I8: 2476
A9: 8 | B9: Ashley Ables | C9: a.ables@hotmail.com | D9: 27 | E9: 7662 | F9: 40.90655 | G9: -74.07797 | H9: =_xlfn.XLOOKUP(Table1[[#This Row],[City_ID]],CITY!$A$2:$A$39,CITY!$D$2:$D$39) -> MidAtlantic | I9: 3252
A10: 9 | B10: Bernarda Caughey | C10: b.caughey@yahoo.com | D10: 37 | E10: 98003 | F10: 47.31107 | G10: -122.31188 | H10: =_xlfn.XLOOKUP(Table1[[#This Row],[City_ID]],CITY!$A$2:$A$39,CITY!$D$2:$D$39) -> West | I10: 4072
A11: 10 | B11: Berniece Blakely | C11: b.blakely@outlook.com | D11: 7 | E11: 94105 | F11: 37.78922 | G11: -122.3957 | H11: =_xlfn.XLOOKUP(Table1[[#This Row],[City_ID]],CITY!$A$2:$A$39,CITY!$D$2:$D$39) -> West | I11: 12125
A12: 11 | B12: Bonita Honaker | C12: b.honaker@aol.com | D12: 31 | E12: 14607 | F12: 43.14986 | G12: -77.58962 | H12: =_xlfn.XLOOKUP(Table1[[#This Row],[City_ID]],CITY!$A$2:$A$39,CITY!$D$2:$D$39) -> MidAtlantic | I12: 7750
A13: 12 | B13: Brittney Edmond | C13: b.edmond@mail.com | D13: 29 | E13: 11377 | F13: 40.74286 | G13: -73.90377 | H13: =_xlfn.XLOOKUP(Table1[[#This Row],[City_ID]],CITY!$A$2:$A$39,CITY!$D$2:$D$39) -> MidAtlantic | I13: 9445
... A101: 100 | B101: Natividad Grandberry | C101: n.grandberry@outlook.com | D101: 6 | E101: 93105 | F101: 34.44005 | G101: -119.75496 | H101: =_xlfn.XLOOKUP(Table1[[#This Row],[City_ID]],CITY!$A$2:$A$39,CITY!$D$2:$D$39) -> West | I101: 9044

Sheet ORDER_DETAILS
A1: Day | B1: Order_ID | C1: Item_ID | D1: Customer_ID | E1: Store_ID | F1: Channel_ID | G1: Unit | H1: Order_Price | I1: Delivery_Charge | J1: Name | K1: Unique Names
A2: 40394 | B2: 10248 | C2: 327 | D2: 1 | E2: 93 | F2: 1 | G2: 8 | H2: 78 | I2: 25 | J2: =_xlfn.XLOOKUP(Table2[[#This Row],[Customer_ID]],Table1[Customer_ID],Table1[Customer_Name]) -> Agatha Clauss | K2: Agatha Clauss | L2: =SUMIFS(Table2[Order_Price],Table3[Name],K2) -> 3921 | M2: 3921
A3: 40394 | B3: 10248 | C3: 425 | D3: 1 | E3: 93 | F3: 1 | G3: 2 | H3: 17 | I3: 25 | J3: =_xlfn.XLOOKUP(Table2[[#This Row],[Customer_ID]],Table1[Customer_ID],Table1[Customer_Name]) -> Agatha Clauss | K3: Alaine Kindig | L3: =SUMIFS(Table2[Order_Price],Table3[Name],K3) -> 3191 | M3: 3191
A4: 40394 | B4: 10248 | C4: 292 | D4: 1 | E4: 93 | F4: 1 | G4: 4 | H4: 4 | I4: 25 | J4: =_xlfn.XLOOKUP(Table2[[#This Row],[Customer_ID]],Table1[Customer_ID],Table1[Customer_Name]) -> Agatha Clauss | K4: Alonzo Stoltz | L4: =SUMIFS(Table2[Order_Price],Table3[Name],K4) -> 4030 | M4: 4030
A5: 40398 | B5: 10250 | C5: 413 | D5: 3 | E5: 40 | F5: 1 | G5: 5 | H5: 20 | I5: 25 | J5: =_xlfn.XLOOKUP(Table2[[#This Row],[Customer_ID]],Table1[Customer_ID],Table1[Customer_Name]) -> Alonzo Stoltz | K5: Andreas Armour | L5: =SUMIFS(Table2[Order_Price],Table3[Name],K5) -> 7313 | M5: 7313
A6: 40398 | B6: 10250 | C6: 428 | D6: 3 | E6: 40 | F6: 1 | G6: 1 | H6: 15 | I6: 25 | J6: =_xlfn.XLOOKUP(Table2[[#This Row],[Customer_ID]],Table1[Customer_ID],Table1[Customer_Name]) -> Alonzo Stoltz | K6: Anette Abdulla | L6: =SUMIFS(Table2[Order_Price],Table3[Name],K6) -> 1152 | M6: 1152
A7: 40398 | B7: 10250 | C7: 254 | D7: 3 | E7: 40 | F7: 1 | G7: 3 | H7: 4 | I7: 25 | J7: =_xlfn.XLOOKUP(Table2[[#This Row],[Customer_ID]],Table1[Customer_ID],Table1[Customer_Name]) -> Alonzo Stoltz | K7: Anjelica Usrey | L7: =SUMIFS(Table2[Order_Price],Table3[Name],K7) -> 775 | M7: 775
A8: 40399 | B8: 10252 | C8: 393 | D8: 5 | E8: 27 | F8: 1 | G8: 1 | H8: 10 | I8: 25 | J8: =_xlfn.XLOOKUP(Table2[[#This Row],[Customer_ID]],Table1[Customer_ID],Table1[Customer_Name]) -> Anette Abdulla | K8: Ardath Peaslee | L8: =SUMIFS(Table2[Order_Price],Table3[Name],K8) -> 2476 | M8: 2476
A9: 40399 | B9: 10252 | C9: 387 | D9: 5 | E9: 27 | F9: 1 | G9: 1 | H9: 7 | I9: 25 | J9: =_xlfn.XLOOKUP(Table2[[#This Row],[Customer_ID]],Table1[Customer_ID],Table1[Customer_Name]) -> Anette Abdulla | K9: Ashley Ables | L9: =SUMIFS(Table2[Order_Price],Table3[Name],K9) -> 3252 | M9: 3252
A10: 40399 | B10: 10252 | C10: 397 | D10: 5 | E10: 27 | F10: 1 | G10: 6 | H10: 12 | I10: 25 | J10: =_xlfn.XLOOKUP(Table2[[#This Row],[Customer_ID]],Table1[Customer_ID],Table1[Customer_Name]) -> Anette Abdulla | K10: Bernarda Caughey | L10: =SUMIFS(Table2[Order_Price],Table3[Name],K10) -> 4072 | M10: 4072
A11: 40401 | B11: 10254 | C11: 186 | D11: 7 | E11: 32 | F11: 1 | G11: 1 | H11: 548 | I11: 25 | J11: =_xlfn.XLOOKUP(Table2[[#This Row],[Customer_ID]],Table1[Customer_ID],Table1[Customer_Name]) -> Ardath Peaslee | K11: Berniece Blakely | L11: =SUMIFS(Table2[Order_Price],Table3[Name],K11) -> 12125 | M11: 12125
A12: 40401 | B12: 10254 | C12: 184 | D12: 7 | E12: 32 | F12: 1 | G12: 3 | H12: 369 | I12: 25 | J12: =_xlfn.XLOOKUP(Table2[[#This Row],[Customer_ID]],Table1[Customer_ID],Table1[Customer_Name]) -> Ardath Peaslee | K12: Bonita Honaker | L12: =SUMIFS(Table2[Order_Price],Table3[Name],K12) -> 7750 | M12: 7750
A13: 40401 | B13: 10254 | C13: 185 | D13: 7 | E13: 32 | F13: 1 | G13: 4 | H13: 505 | I13: 25 | J13: =_xlfn.XLOOKUP(Table2[[#This Row],[Customer_ID]],Table1[Customer_ID],Table1[Customer_Name]) -> Ardath Peaslee | K13: Brittney Edmond | L13: =SUMIFS(Table2[Order_Price],Table3[Name],K13) -> 9445 | M13: 9445
... A101: 40490 | B101: 10324 | C101: 128 | D101: 77 | E101: 4 | F101: 1 | G101: 3 | H101: 644 | I101: 25 | J101: =_xlfn.XLOOKUP(Table2[[#This Row],[Customer_ID]],Table1[Customer_ID],Table1[Customer_Name]) -> Kyla Danek | K101: Natividad Grandberry | L101: =SUMIFS(Table2[Order_Price],Table3[Name],K101) -> 9044 | M101: 9044
A102: 40490 | B102: 10324 | C102: 126 | D102: 77 | E102: 4 | F102: 1 | G102: 8 | H102: 450 | I102: 25 | J102: =_xlfn.XLOOKUP(Table2[[#This Row],[Customer_ID]],Table1[Customer_ID],Table1[Customer_Name]) -> Kyla Danek
A103: 40490 | B103: 10324 | C103: 262 | D103: 77 | E103: 4 | F103: 1 | G103: 1 | H103: 3 | I103: 25 | J103: =_xlfn.XLOOKUP(Table2[[#This Row],[Customer_ID]],Table1[Customer_ID],Table1[Customer_Name]) -> Kyla Danek
A104: 40490 | B104: 10324 | C104: 269 | D104: 77 | E104: 4 | F104: 1 | G104: 2 | H104: 3 | I104: 25 | J104: =_xlfn.XLOOKUP(Table2[[#This Row],[Customer_ID]],Table1[Customer_ID],Table1[Customer_Name]) -> Kyla Danek
A105: 40490 | B105: 10324 | C105: 127 | D105: 77 | E105: 4 | F105: 1 | G105: 1 | H105: 695 | I105: 25 | J105: =_xlfn.XLOOKUP(Table2[[#This Row],[Customer_ID]],Table1[Customer_ID],Table1[Customer_Name]) -> Kyla Danek
A106: 40492 | B106: 10326 | C106: 361 | D106: 79 | E106: 1 | F106: 1 | G106: 6 | H106: 123 | I106: 25 | J106: =_xlfn.XLOOKUP(Table2[[#This Row],[Customer_ID]],Table1[Customer_ID],Table1[Customer_Name]) -> Lala Ladue
A107: 40492 | B107: 10326 | C107: 352 | D107: 79 | E107: 1 | F107: 1 | G107: 2 | H107: 89 | I107: 25 | J107: =_xlfn.XLOOKUP(Table2[[#This Row],[Customer_ID]],Table1[Customer_ID],Table1[Customer_Name]) -> Lala Ladue
A108: 40492 | B108: 10326 | C108: 197 | D108: 79 | E108: 1 | F108: 1 | G108: 3 | H108: 3 | I108: 25 | J108: =_xlfn.XLOOKUP(Table2[[#This Row],[Customer_ID]],Table1[Customer_ID],Table1[Customer_Name]) -> Lala Ladue
A109: 40496 | B109: 10328 | C109: 382 | D109: 81 | E109: 96 | F109: 1 | G109: 6 | H109: 5 | I109: 25 | J109: =_xlfn.XLOOKUP(Table2[[#This Row],[Customer_ID]],Table1[Customer_ID],Table1[Customer_Name]) -> Leanne Lockhart
A110: 40496 | B110: 10328 | C110: 383 | D110: 81 | E110: 96 | F110: 1 | G110: 2 | H110: 9 | I110: 25 | J110: =_xlfn.XLOOKUP(Table2[[#This Row],[Customer_ID]],Table1[Customer_ID],Table1[Customer_Name]) -> Leanne Lockhart
A111: 40496 | B111: 10328 | C111: 375 | D111: 81 | E111: 96 | F111: 1 | G111: 8 | H111: 5 | I111: 25 | J111: =_xlfn.XLOOKUP(Table2[[#This Row],[Customer_ID]],Table1[Customer_ID],Table1[Customer_Name]) -> Leanne Lockhart
A112: 40498 | B112: 10330 | C112: 380 | D112: 83 | E112: 25 | F112: 1 | G112: 5 | H112: 9 | I112: 25 | J112: =_xlfn.XLOOKUP(Table2[[#This Row],[Customer_ID]],Table1[Customer_ID],Table1[Customer_Name]) -> Lily Weatherford
A113: 40498 | B113: 10330 | C113: 374 | D113: 83 | E113: 25 | F113: 1 | G113: 4 | H113: 9 | I113: 25 | J113: =_xlfn.XLOOKUP(Table2[[#This Row],[Customer_ID]],Table1[Customer_ID],Table1[Customer_Name]) -> Lily Weatherford
... A220: 40587 | B220: 10412 | C220: 372 | D220: 65 | E220: 31 | F220: 1 | G220: 1 | H220: 9 | I220: 25 | J220: =_xlfn.XLOOKUP(Table2[[#This Row],[Customer_ID]],Table1[Customer_ID],Table1[Customer_Name]) -> Judie Sawicki
A221: 40588 | B221: 10414 | C221: 390 | D221: 67 | F221: 1 | G221: 2 | H221: 11 | I221: 25 | J221: =_xlfn.XLOOKUP(Table2[[#This Row],[Customer_ID]],Table1[Customer_ID],Table1[Customer_Name]) -> Kaitlyn Killian
A222: 40588 | B222: 10414 | C222: 389 | D222: 67 | F222: 1 | G222: 1 | H222: 8 | I222: 25 | J222: =_xlfn.XLOOKUP(Table2[[#This Row],[Customer_ID]],Table1[Customer_ID],Table1[Customer_Name]) -> Kaitlyn Killian
A223: 40590 | B223: 10416 | C223: 451 | D223: 69 | F223: 1 | G223: 3 | H223: 19 | I223: 25 | J223: =_xlfn.XLOOKUP(Table2[[#This Row],[Customer_ID]],Table1[Customer_ID],Table1[Customer_Name]) -> Kareem Koser
A224: 40590 | B224: 10416 | C224: 444 | D224: 69 | F224: 1 | G224: 2 | H224: 35 | I224: 25 | J224: =_xlfn.XLOOKUP(Table2[[#This Row],[Customer_ID]],Table1[Customer_ID],Table1[Customer_Name]) -> Kareem Koser
A225: 40590 | B225: 10416 | C225: 453 | D225: 69 | F225: 1 | G225: 1 | H225: 19 | I225: 25 | J225: =_xlfn.XLOOKUP(Table2[[#This Row],[Customer_ID]],Table1[Customer_ID],Table1[Customer_Name]) -> Kareem Koser
A226: 40591 | B226: 10418 | C226: 432 | D226: 71 | F226: 1 | G226: 5 | H226: 50 | I226: 25 | J226: =_xlfn.XLOOKUP(Table2[[#This Row],[Customer_ID]],Table1[Customer_ID],Table1[Customer_Name]) -> Karissa Kircher
A227: 40591 | B227: 10418 | C227: 456 | D227: 71 | F227: 1 | G227: 7 | H227: 16 | I227: 25 | J227: =_xlfn.XLOOKUP(Table2[[#This Row],[Customer_ID]],Table1[Customer_ID],Table1[Customer_Name]) -> Karissa Kircher
A228: 40591 | B228: 10418 | C228: 431 | D228: 71 | F228: 1 | G228: 3 | H228: 15 | I228: 25 | J228: =_xlfn.XLOOKUP(Table2[[#This Row],[Customer_ID]],Table1[Customer_ID],Table1[Customer_Name]) -> Karissa Kircher
A229: 40591 | B229: 10418 | C229: 38 | D229: 71 | F229: 1 | G229: 1 | H229: 8 | I229: 25 | J229: =_xlfn.XLOOKUP(Table2[[#This Row],[Customer_ID]],Table1[Customer_ID],Table1[Customer_Name]) -> Karissa Kircher
A230: 40595 | B230: 10420 | C230: 414 | D230: 73 | F230: 1 | G230: 3 | H230: 16 | I230: 25 | J230: =_xlfn.XLOOKUP(Table2[[#This Row],[Customer_ID]],Table1[Customer_ID],Table1[Customer_Name]) -> Katharine Pearcy
A231: 40595 | B231: 10420 | C231: 426 | D231: 73 | F231: 1 | G231: 2 | H231: 7 | I231: 25 | J231: =_xlfn.XLOOKUP(Table2[[#This Row],[Customer_ID]],Table1[Customer_ID],Table1[Customer_Name]) -> Katharine Pearcy
A232: 40595 | B232: 10420 | C232: 413 | D232: 73 | F232: 1 | G232: 4 | H232: 20 | I232: 25 | J232: =_xlfn.XLOOKUP(Table2[[#This Row],[Customer_ID]],Table1[Customer_ID],Table1[Customer_Name]) -> Katharine Pearcy
... A270: 40619 | B270: 10446 | C270: 364 | D270: 99 | F270: 1 | G270: 2 | H270: 6 | I270: 25 | J270: =_xlfn.XLOOKUP(Table2[[#This Row],[Customer_ID]],Table1[Customer_ID],Table1[Customer_Name]) -> Nana Nolette
A271: 40622 | B271: 10448 | C271: 100 | D271: 1 | E271: 93 | F271: 1 | G271: 2 | H271: 1577 | I271: 25 | J271: =_xlfn.XLOOKUP(Table2[[#This Row],[Customer_ID]],Table1[Customer_ID],Table1[Customer_Name]) -> Agatha Clauss
A272: 40622 | B272: 10448 | C272: 101 | D272: 1 | E272: 93 | F272: 1 | G272: 6 | H272: 706 | I272: 25 | J272: =_xlfn.XLOOKUP(Table2[[#This Row],[Customer_ID]],Table1[Customer_ID],Table1[Customer_Name]) -> Agatha Clauss
A273: 40624 | B273: 10450 | C273: 91 | D273: 3 | E273: 40 | F273: 1 | G273: 2 | H273: 480 | I273: 25 | J273: =_xlfn.XLOOKUP(Table2[[#This Row],[Customer_ID]],Table1[Customer_ID],Table1[Customer_Name]) -> Alonzo Stoltz
A274: 40624 | B274: 10450 | C274: 89 | D274: 3 | E274: 40 | F274: 1 | G274: 4 | H274: 543 | I274: 25 | J274: =_xlfn.XLOOKUP(Table2[[#This Row],[Customer_ID]],Table1[Customer_ID],Table1[Customer_Name]) -> Alonzo Stoltz
A275: 40625 | B275: 10452 | C275: 430 | D275: 5 | E275: 28 | F275: 1 | G275: 2 | H275: 18 | I275: 25 | J275: =_xlfn.XLOOKUP(Table2[[#This Row],[Customer_ID]],Table1[Customer_ID],Table1[Customer_Name]) -> Anette Abdulla
A276: 40625 | B276: 10452 | C276: 440 | D276: 5 | E276: 28 | F276: 1 | G276: 6 | H276: 38 | I276: 25 | J276: =_xlfn.XLOOKUP(Table2[[#This Row],[Customer_ID]],Table1[Customer_ID],Table1[Customer_Name]) -> Anette Abdulla
A277: 40626 | B277: 10454 | C277: 452 | D277: 7 | E277: 32 | F277: 1 | G277: 1 | H277: 24 | I277: 25 | J277: =_xlfn.XLOOKUP(Table2[[#This Row],[Customer_ID]],Table1[Customer_ID],Table1[Customer_Name]) -> Ardath Peaslee
A278: 40626 | B278: 10454 | C278: 448 | D278: 7 | E278: 32 | F278: 1 | G278: 7 | H278: 47 | I278: 25 | J278: =_xlfn.XLOOKUP(Table2[[#This Row],[Customer_ID]],Table1[Customer_ID],Table1[Customer_Name]) -> Ardath Peaslee
A279: 40626 | B279: 10454 | C279: 420 | D279: 7 | E279: 32 | F279: 1 | G279: 2 | H279: 17 | I279: 25 | J279: =_xlfn.XLOOKUP(Table2[[#This Row],[Customer_ID]],Table1[Customer_ID],Table1[Customer_Name]) -> Ardath Peaslee
A280: 40630 | B280: 10456 | C280: 59 | D280: 9 | E280: 97 | F280: 1 | G280: 1 | H280: 11 | I280: 25 | J280: =_xlfn.XLOOKUP(Table2[[#This Row],[Customer_ID]],Table1[Customer_ID],Table1[Customer_Name]) -> Bernarda Caughey
A281: 40630 | B281: 10456 | C281: 251 | D281: 9 | E281: 97 | F281: 1 | G281: 5 | H281: 25 | I281: 25 | J281: =_xlfn.XLOOKUP(Table2[[#This Row],[Customer_ID]],Table1[Customer_ID],Table1[Customer_Name]) -> Bernarda Caughey
A282: 40631 | B282: 10458 | C282: 333 | D282: 11 | E282: 78 | F282: 1 | G282: 2 | H282: 46 | I282: 25 | J282: =_xlfn.XLOOKUP(Table2[[#This Row],[Customer_ID]],Table1[Customer_ID],Table1[Customer_Name]) -> Bonita Honaker
... A350: 40685 | B350: 10512 | C350: 424 | D350: 65 | E350: 31 | F350: 1 | G350: 2 | H350: 12 | I350: 25 | J350: =_xlfn.XLOOKUP(Table2[[#This Row],[Customer_ID]],Table1[Customer_ID],Table1[Customer_Name]) -> Judie Sawicki
A351: 40686 | B351: 10514 | C351: 217 | D351: 67 | F351: 1 | G351: 5 | H351: 4 | I351: 25 | J351: =_xlfn.XLOOKUP(Table2[[#This Row],[Customer_ID]],Table1[Customer_ID],Table1[Customer_Name]) -> Kaitlyn Killian
A352: 40686 | B352: 10514 | C352: 272 | D352: 67 | F352: 1 | G352: 7 | H352: 2 | I352: 25 | J352: =_xlfn.XLOOKUP(Table2[[#This Row],[Customer_ID]],Table1[Customer_ID],Table1[Customer_Name]) -> Kaitlyn Killian
A353: 40686 | B353: 10514 | C353: 406 | D353: 67 | F353: 1 | G353: 2 | H353: 20 | I353: 25 | J353: =_xlfn.XLOOKUP(Table2[[#This Row],[Customer_ID]],Table1[Customer_ID],Table1[Customer_Name]) -> Kaitlyn Killian
A354: 40686 | B354: 10514 | C354: 407 | D354: 67 | F354: 1 | G354: 2 | H354: 16 | I354: 25 | J354: =_xlfn.XLOOKUP(Table2[[#This Row],[Customer_ID]],Table1[Customer_ID],Table1[Customer_Name]) -> Kaitlyn Killian
A355: 40686 | B355: 10514 | C355: 220 | D355: 67 | F355: 1 | G355: 5 | H355: 5 | I355: 25 | J355: =_xlfn.XLOOKUP(Table2[[#This Row],[Customer_ID]],Table1[Customer_ID],Table1[Customer_Name]) -> Kaitlyn Killian
A356: 40688 | B356: 10516 | C356: 279 | D356: 69 | F356: 1 | G356: 2 | H356: 4 | I356: 25 | J356: =_xlfn.XLOOKUP(Table2[[#This Row],[Customer_ID]],Table1[Customer_ID],Table1[Customer_Name]) -> Kareem Koser
A357: 40688 | B357: 10516 | C357: 282 | D357: 69 | F357: 1 | G357: 1 | H357: 3 | I357: 25 | J357: =_xlfn.XLOOKUP(Table2[[#This Row],[Customer_ID]],Table1[Customer_ID],Table1[Customer_Name]) -> Kareem Koser
A358: 40688 | B358: 10516 | C358: 275 | D358: 69 | F358: 1 | G358: 1 | H358: 3 | I358: 25 | J358: =_xlfn.XLOOKUP(Table2[[#This Row],[Customer_ID]],Table1[Customer_ID],Table1[Customer_Name]) -> Kareem Koser
A359: 40689 | B359: 10518 | C359: 136 | D359: 71 | F359: 1 | G359: 2 | H359: 90 | I359: 25 | J359: =_xlfn.XLOOKUP(Table2[[#This Row],[Customer_ID]],Table1[Customer_ID],Table1[Customer_Name]) -> Karissa Kircher
A360: 40689 | B360: 10518 | C360: 134 | D360: 71 | F360: 1 | G360: 1 | H360: 90 | I360: 25 | J360: =_xlfn.XLOOKUP(Table2[[#This Row],[Customer_ID]],Table1[Customer_ID],Table1[Customer_Name]) -> Karissa Kircher
A361: 40689 | B361: 10518 | C361: 148 | D361: 71 | F361: 1 | G361: 8 | H361: 444 | I361: 25 | J361: =_xlfn.XLOOKUP(Table2[[#This Row],[Customer_ID]],Table1[Customer_ID],Table1[Customer_Name]) -> Karissa Kircher
A362: 40693 | B362: 10520 | C362: 149 | D362: 73 | F362: 1 | G362: 5 | H362: 717 | I362: 25 | J362: =_xlfn.XLOOKUP(Table2[[#This Row],[Customer_ID]],Table1[Customer_ID],Table1[Customer_Name]) -> Katharine Pearcy
... A403: 40717 | B403: 10546 | C403: 7 | D403: 99 | F403: 1 | G403: 4 | H403: 395 | I403: 25 | J403: =_xlfn.XLOOKUP(Table2[[#This Row],[Customer_ID]],Table1[Customer_ID],Table1[Customer_Name]) -> Nana Nolette
A404: 40720 | B404: 10548 | C404: 84 | D404: 1 | E404: 94 | F404: 1 | G404: 3 | H404: 6 | I404: 25 | J404: =_xlfn.XLOOKUP(Table2[[#This Row],[Customer_ID]],Table1[Customer_ID],Table1[Customer_Name]) -> Agatha Clauss
A405: 40720 | B405: 10548 | C405: 49 | D405: 1 | E405: 94 | F405: 1 | G405: 9 | H405: 30 | I405: 25 | J405: =_xlfn.XLOOKUP(Table2[[#This Row],[Customer_ID]],Table1[Customer_ID],Table1[Customer_Name]) -> Agatha Clauss
A406: 40722 | B406: 10550 | C406: 124 | D406: 3 | E406: 41 | F406: 1 | G406: 1 | H406: 522 | I406: 25 | J406: =_xlfn.XLOOKUP(Table2[[#This Row],[Customer_ID]],Table1[Customer_ID],Table1[Customer_Name]) -> Alonzo Stoltz
A407: 40722 | B407: 10550 | C407: 125 | D407: 3 | E407: 41 | F407: 1 | G407: 5 | H407: 930 | I407: 25 | J407: =_xlfn.XLOOKUP(Table2[[#This Row],[Customer_ID]],Table1[Customer_ID],Table1[Customer_Name]) -> Alonzo Stoltz
A408: 40722 | B408: 10550 | C408: 121 | D408: 3 | E408: 41 | F408: 1 | G408: 1 | H408: 763 | I408: 25 | J408: =_xlfn.XLOOKUP(Table2[[#This Row],[Customer_ID]],Table1[Customer_ID],Table1[Customer_Name]) -> Alonzo Stoltz
A409: 40722 | B409: 10550 | C409: 122 | D409: 3 | E409: 41 | F409: 1 | G409: 1 | H409: 433 | I409: 25 | J409: =_xlfn.XLOOKUP(Table2[[#This Row],[Customer_ID]],Table1[Customer_ID],Table1[Customer_Name]) -> Alonzo Stoltz
A410: 40723 | B410: 10552 | C410: 80 | D410: 5 | E410: 27 | F410: 1 | G410: 15 | H410: 23 | I410: 25 | J410: =_xlfn.XLOOKUP(Table2[[#This Row],[Customer_ID]],Table1[Customer_ID],Table1[Customer_Name]) -> Anette Abdulla
A411: 40723 | B411: 10552 | C411: 71 | D411: 5 | E411: 27 | F411: 1 | G411: 3 | H411: 12 | I411: 25 | J411: =_xlfn.XLOOKUP(Table2[[#This Row],[Customer_ID]],Table1[Customer_ID],Table1[Customer_Name]) -> Anette Abdulla
A412: 40724 | B412: 10554 | C412: 195 | D412: 7 | E412: 32 | F412: 1 | G412: 3 | H412: 6 | I412: 25 | J412: =_xlfn.XLOOKUP(Table2[[#This Row],[Customer_ID]],Table1[Customer_ID],Table1[Customer_Name]) -> Ardath Peaslee
A413: 40724 | B413: 10554 | C413: 252 | D413: 7 | E413: 32 | F413: 1 | G413: 6 | H413: 27 | I413: 25 | J413: =_xlfn.XLOOKUP(Table2[[#This Row],[Customer_ID]],Table1[Customer_ID],Table1[Customer_Name]) -> Ardath Peaslee
A414: 40724 | B414: 10554 | C414: 299 | D414: 7 | E414: 32 | F414: 1 | G414: 1 | H414: 3 | I414: 25 | J414: =_xlfn.XLOOKUP(Table2[[#This Row],[Customer_ID]],Table1[Customer_ID],Table1[Customer_Name]) -> Ardath Peaslee
A415: 40724 | B415: 10554 | C415: 234 | D415: 7 | E415: 32 | F415: 1 | G415: 3 | H415: 27 | I415: 25 | J415: =_xlfn.XLOOKUP(Table2[[#This Row],[Customer_ID]],Table1[Customer_ID],Table1[Customer_Name]) -> Ardath Peaslee
... A494: 40791 | B494: 10620 | C494: 365 | D494: 73 | E494: 16 | F494: 1 | G494: 7 | H494: 7 | I494: 25 | J494: =_xlfn.XLOOKUP(Table2[[#This Row],[Customer_ID]],Table1[Customer_ID],Table1[Customer_Name]) -> Katharine Pearcy
A495: 40792 | B495: 10622 | C495: 101 | D495: 75 | F495: 1 | G495: 3 | H495: 706 | I495: 25 | J495: =_xlfn.XLOOKUP(Table2[[#This Row],[Customer_ID]],Table1[Customer_ID],Table1[Customer_Name]) -> Keisha Koh
A496: 40792 | B496: 10622 | C496: 102 | D496: 75 | F496: 1 | G496: 5 | H496: 495 | I496: 25 | J496: =_xlfn.XLOOKUP(Table2[[#This Row],[Customer_ID]],Table1[Customer_ID],Table1[Customer_Name]) -> Keisha Koh
A497: 40793 | B497: 10624 | C497: 93 | D497: 77 | F497: 1 | G497: 1 | H497: 712 | I497: 25 | J497: =_xlfn.XLOOKUP(Table2[[#This Row],[Customer_ID]],Table1[Customer_ID],Table1[Customer_Name]) -> Kyla Danek
A498: 40793 | B498: 10624 | C498: 91 | D498: 77 | F498: 1 | G498: 3 | H498: 480 | I498: 25 | J498: =_xlfn.XLOOKUP(Table2[[#This Row],[Customer_ID]],Table1[Customer_ID],Table1[Customer_Name]) -> Kyla Danek
A499: 40793 | B499: 10624 | C499: 94 | D499: 77 | F499: 1 | G499: 1 | H499: 487 | I499: 25 | J499: =_xlfn.XLOOKUP(Table2[[#This Row],[Customer_ID]],Table1[Customer_ID],Table1[Customer_Name]) -> Kyla Danek
A500: 40797 | B500: 10626 | C500: 423 | D500: 79 | F500: 1 | G500: 1 | H500: 18 | I500: 25 | J500: =_xlfn.XLOOKUP(Table2[[#This Row],[Customer_ID]],Table1[Customer_ID],Table1[Customer_Name]) -> Lala Ladue
A501: 40797 | B501: 10626 | C501: 445 | D501: 79 | F501: 1 | G501: 2 | H501: 46 | I501: 25 | J501: =_xlfn.XLOOKUP(Table2[[#This Row],[Customer_ID]],Table1[Customer_ID],Table1[Customer_Name]) -> Lala Ladue
A502: 40797 | B502: 10626 | C502: 430 | D502: 79 | F502: 1 | G502: 2 | H502: 18 | I502: 25 | J502: =_xlfn.XLOOKUP(Table2[[#This Row],[Customer_ID]],Table1[Customer_ID],Table1[Customer_Name]) -> Lala Ladue
A503: 40798 | B503: 10628 | C503: 448 | D503: 81 | F503: 1 | G503: 8 | H503: 47 | I503: 25 | J503: =_xlfn.XLOOKUP(Table2[[#This Row],[Customer_ID]],Table1[Customer_ID],Table1[Customer_Name]) -> Leanne Lockhart
A504: 40799 | B504: 10630 | C504: 434 | D504: 83 | F504: 1 | G504: 2 | H504: 24 | I504: 25 | J504: =_xlfn.XLOOKUP(Table2[[#This Row],[Customer_ID]],Table1[Customer_ID],Table1[Customer_Name]) -> Lily Weatherford
A505: 40799 | B505: 10630 | C505: 236 | D505: 83 | F505: 1 | G505: 4 | H505: 28 | I505: 25 | J505: =_xlfn.XLOOKUP(Table2[[#This Row],[Customer_ID]],Table1[Customer_ID],Table1[Customer_Name]) -> Lily Weatherford
A506: 40800 | B506: 10632 | C506: 58 | D506: 85 | F506: 1 | G506: 2 | H506: 14 | I506: 25 | J506: =_xlfn.XLOOKUP(Table2[[#This Row],[Customer_ID]],Table1[Customer_ID],Table1[Customer_Name]) -> Lissette Layton
... A527: 40813 | B527: 10646 | C527: 256 | D527: 99 | F527: 1 | G527: 4 | H527: 5 | I527: 25 | J527: =_xlfn.XLOOKUP(Table2[[#This Row],[Customer_ID]],Table1[Customer_ID],Table1[Customer_Name]) -> Nana Nolette
A528: 40814 | B528: 10648 | C528: 225 | D528: 1 | E528: 93 | F528: 1 | G528: 5 | H528: 3 | I528: 25 | J528: =_xlfn.XLOOKUP(Table2[[#This Row],[Customer_ID]],Table1[Customer_ID],Table1[Customer_Name]) -> Agatha Clauss
A529: 40814 | B529: 10648 | C529: 305 | D529: 1 | E529: 93 | F529: 1 | G529: 9 | H529: 4 | I529: 25 | J529: =_xlfn.XLOOKUP(Table2[[#This Row],[Customer_ID]],Table1[Customer_ID],Table1[Customer_Name]) -> Agatha Clauss
A530: 40815 | B530: 10650 | C530: 367 | D530: 3 | E530: 40 | F530: 1 | G530: 5 | H530: 10 | I530: 25 | J530: =_xlfn.XLOOKUP(Table2[[#This Row],[Customer_ID]],Table1[Customer_ID],Table1[Customer_Name]) -> Alonzo Stoltz
A531: 40815 | B531: 10650 | C531: 362 | D531: 3 | E531: 40 | F531: 1 | G531: 2 | H531: 4 | I531: 25 | J531: =_xlfn.XLOOKUP(Table2[[#This Row],[Customer_ID]],Table1[Customer_ID],Table1[Customer_Name]) -> Alonzo Stoltz
A532: 40815 | B532: 10650 | C532: 363 | D532: 3 | E532: 40 | F532: 1 | G532: 7 | H532: 2 | I532: 25 | J532: =_xlfn.XLOOKUP(Table2[[#This Row],[Customer_ID]],Table1[Customer_ID],Table1[Customer_Name]) -> Alonzo Stoltz
A533: 40818 | B533: 10652 | C533: 285 | D533: 5 | E533: 28 | F533: 1 | G533: 2 | H533: 5 | I533: 25 | J533: =_xlfn.XLOOKUP(Table2[[#This Row],[Customer_ID]],Table1[Customer_ID],Table1[Customer_Name]) -> Anette Abdulla
A534: 40818 | B534: 10652 | C534: 227 | D534: 5 | E534: 28 | F534: 1 | G534: 4 | H534: 4 | I534: 25 | J534: =_xlfn.XLOOKUP(Table2[[#This Row],[Customer_ID]],Table1[Customer_ID],Table1[Customer_Name]) -> Anette Abdulla
A535: 40819 | B535: 10654 | C535: 240 | D535: 7 | E535: 32 | F535: 1 | G535: 1 | H535: 26 | I535: 25 | J535: =_xlfn.XLOOKUP(Table2[[#This Row],[Customer_ID]],Table1[Customer_ID],Table1[Customer_Name]) -> Ardath Peaslee
...

Sheet REGION
A1: Region_ID | B1: Region_Name | C1: Country_ID
A2: 1 | B2: NorthEast | C2: 1
A3: 2 | B3: MidAtlantic | C3: 1
A4: 3 | B4: South | C4: 1
A5: 4 | B5: West | C5: 1

Sheet STORE
A1: Store_ID | B1: Store Code | C1: Zipcode | D1: Store_Name | E1: City_ID | F1: Latitude | G1: Longitude
A2: 1 | B2: wm_85016 | C2: 85016 | D2: Wallmart | E2: 1 | F2: 33.50374 | G2: -112.03235
A3: 2 | B3: wm_85018 | C3: 85018 | D3: Wallmart | E3: 1 | F3: 33.49807 | G3: -111.98603
A4: 3 | B4: wm_85021 | C4: 85021 | D4: Wallmart | E4: 1 | F4: 33.55943 | G4: -112.09281
A5: 4 | B5: wm_85251 | C5: 85251 | D5: Wallmart | E5: 2 | F5: 33.49415 | G5: -111.92079
A6: 5 | B6: wm_85253 | C6: 85253 | D6: Wallmart | E6: 2 | F6: 33.54459 | G6: -111.95645
A7: 6 | B7: wm_85254 | C7: 85254 | D7: Wallmart | E7: 2 | F7: 33.6175 | G7: -111.95416
A8: 7 | B8: wm_90211 | C8: 90211 | D8: Wallmart | E8: 3 | F8: 34.066 | G8: -118.38271
A9: 8 | B9: wm_90210 | C9: 90210 | D9: Wallmart | E9: 3 | F9: 34.0888 | G9: -118.40612
A10: 9 | B10: wm_90035 | C10: 90035 | D10: Wallmart | E10: 3 | F10: 34.05266 | G10: -118.38531
A11: 10 | B11: wm_90212 | C11: 90212 | D11: Wallmart | E11: 3 | F11: 34.06085 | G11: -118.40191
A12: 11 | B12: wm_90011 | C12: 90011 | D12: Wallmart | E12: 4 | F12: 34.00706 | G12: -118.25868
A13: 12 | B13: wm_90017 | C13: 90017 | D13: Wallmart | E13: 4 | F13: 34.05256 | G13: -118.26434
... A101: 100 | B101: wm_98122 | C101: 98122 | D101: Wallmart | E101: 38 | F101: 47.61157 | G101: -122.30406

Sheet YEAR
A1: Year_ID
A2: 2010
A3: 2011
A4: 2012
A5: 2013

Sheet ITEM
A1: ITEM_ID | B1: ITEM | C1: SUBCAT_ID | D1: Price
A2: 1 | B2: Samsung Galaxy S 4 | C2: 1 | D2: 702
A3: 2 | B3: Samsung Galaxy Note II | C3: 1 | D3: 634
A4: 3 | B4: Samsung Galaxy Mega 6.3 | C4: 1 | D4: 532
A5: 4 | B5: Samsung Galaxy Beam | C5: 1 | D5: 506
A6: 5 | B6: Samsung Galaxy S4 Zoom | C6: 1 | D6: 497
A7: 6 | B7: Samsung Galaxy S III | C7: 1 | D7: 489
A8: 7 | B8: Samsung Galaxy SII Plus | C8: 1 | D8: 395
A9: 8 | B9: Samsung Galaxy Note | C9: 1 | D9: 380
A10: 9 | B10: Samsung Galaxy Grand | C10: 1 | D10: 336
A11: 10 | B11: Samsung Wave M | C11: 1 | D11: 236
A12: 11 | B12: Samsung Galaxy Ace Duos | C12: 1 | D12: 208
A13: 12 | B13: Nokia Lumia 920 | C13: 1 | D13: 592
... A458: 457 | B458: Wrangler - Men's Rip-Stop Cargo Pants | C458: 34 | D458: 19

Sheet DAY
A1: Day | B1: Month_ID
A2: 40179 | B2: 201001
A3: 40180 | B3: 201001
A4: 40181 | B4: 201001
A5: 40182 | B5: 201001
A6: 40183 | B6: 201001
A7: 40184 | B7: 201001
A8: 40185 | B8: 201001
A9: 40186 | B9: 201001
A10: 40187 | B10: 201001
A11: 40188 | B11: 201001
A12: 40189 | B12: 201001
A13: 40190 | B13: 201001
... A1097: 41274 | B1097: 201212

Sheet CHANNEL
A1: Channel_ID | B1: Channel_Name | C1: Payment
A2: 1 | B2: Web Store | C2: Cash on Delivery
A3: 2 | B3: Retail Store | C3: Card Payment

Sheet CITY
A1: City_ID | B1: City_Name | C1: State_ID | D1: Region
A2: 1 | B2: Phoenix | C2: 1 | D2: =_xlfn.XLOOKUP(C2,STATE!$A$2:$A$11,STATE!$D$2:$D$11) -> West
A3: 2 | B3: Scottsdale | C3: 1 | D3: =_xlfn.XLOOKUP(C3,STATE!$A$2:$A$11,STATE!$D$2:$D$11) -> West
A4: 3 | B4: Beverly Hills | C4: 2 | D4: =_xlfn.XLOOKUP(C4,STATE!$A$2:$A$11,STATE!$D$2:$D$11) -> West
A5: 4 | B5: Los Angeles | C5: 2 | D5: =_xlfn.XLOOKUP(C5,STATE!$A$2:$A$11,STATE!$D$2:$D$11) -> West
A6: 5 | B6: Northridge | C6: 2 | D6: =_xlfn.XLOOKUP(C6,STATE!$A$2:$A$11,STATE!$D$2:$D$11) -> West
A7: 6 | B7: Oxnard | C7: 2 | D7: =_xlfn.XLOOKUP(C7,STATE!$A$2:$A$11,STATE!$D$2:$D$11) -> West
A8: 7 | B8: San Francisco | C8: 2 | D8: =_xlfn.XLOOKUP(C8,STATE!$A$2:$A$11,STATE!$D$2:$D$11) -> West
A9: 8 | B9: Santa Barbara | C9: 2 | D9: =_xlfn.XLOOKUP(C9,STATE!$A$2:$A$11,STATE!$D$2:$D$11) -> West
A10: 9 | B10: Van Nuys | C10: 2 | D10: =_xlfn.XLOOKUP(C10,STATE!$A$2:$A$11,STATE!$D$2:$D$11) -> West
A11: 10 | B11: Hartford | C11: 3 | D11: =_xlfn.XLOOKUP(C11,STATE!$A$2:$A$11,STATE!$D$2:$D$11) -> NorthEast
A12: 11 | B12: Waterbury | C12: 3 | D12: =_xlfn.XLOOKUP(C12,STATE!$A$2:$A$11,STATE!$D$2:$D$11) -> NorthEast
A13: 12 | B13: West Haven | C13: 3 | D13: =_xlfn.XLOOKUP(C13,STATE!$A$2:$A$11,STATE!$D$2:$D$11) -> NorthEast
... A39: 38 | B39: Seattle | C39: 10 | D39: =_xlfn.XLOOKUP(C39,STATE!$A$2:$A$11,STATE!$D$2:$D$11) -> West

Sheet COUNTRY
A1: Country_ID | B1: Country_Name
A2: 1 | B2: United States of America

Sheet SUBCATEGORY
A1: SUBCAT_ID | B1: SUBCATEGORY | C1: CATEGORY_ID
A2: 1 | B2: SmartPhones | C2: 1
A3: 2 | B3: Headsets | C3: 1
A4: 3 | B4: Chargers | C4: 1
A5: 4 | B5: Memory Cards | C5: 1
A6: 5 | B6: Dell | C6: 2
A7: 6 | B7: HP | C7: 2
A8: 7 | B8: Apple | C8: 2
A9: 8 | B9: Samsung | C9: 2
A10: 9 | B10: Lenovo | C10: 2
A11: 10 | B11: Point & Shoot | C11: 3
A12: 11 | B12: SLR | C12: 3
A13: 12 | B13: Camcorder | C13: 3
... A35: 34 | B35: Jeans and Pants | C35: 11

Sheet CATEGORY
A1: CATEGORY_ID | B1: CATEGORY_NAME | C1: DEPARTMENT_ID
A2: 1 | B2: Cell Phones & Accessories | C2: 1
A3: 2 | B3: Laptops | C3: 1
A4: 3 | B4: Cameras | C4: 1
A5: 4 | B5: Tablets | C5: 1
A6: 5 | B6: Beverages | C6: 2
A7: 6 | B7: Condiments, Sauces and Spices | C7: 2
A8: 7 | B8: Snacks & Cookies | C8: 2
A9: 8 | B9: Fresh Food | C9: 2
A10: 9 | B10: Produce | C10: 2
A11: 10 | B11: Women | C11: 3
A12: 11 | B12: Men | C12: 3

Sheet DEPARTMENT
A1: DEPARTMENT_ID | B1: DEPARTMENT_NAME
A2: 1 | B2: Electronics
A3: 2 | B3: Grocery
A4: 3 | B4: Clothing

Sheet STATE
A1: State_ID | B1: State_Name | C1: Region_ID
A2: 1 | B2: Arizona | C2: 4 | D2: =_xlfn.XLOOKUP(C2,REGION!$A$2:$A$5,REGION!$B$2:$B$5) -> West
A3: 2 | B3: California | C3: 4 | D3: =_xlfn.XLOOKUP(C3,REGION!$A$2:$A$5,REGION!$B$2:$B$5) -> West
A4: 3 | B4: Connecticut | C4: 1 | D4: =_xlfn.XLOOKUP(C4,REGION!$A$2:$A$5,REGION!$B$2:$B$5) -> NorthEast
A5: 4 | B5: Florida | C5: 3 | D5: =_xlfn.XLOOKUP(C5,REGION!$A$2:$A$5,REGION!$B$2:$B$5) -> South
A6: 5 | B6: Massachusetts | C6: 1 | D6: =_xlfn.XLOOKUP(C6,REGION!$A$2:$A$5,REGION!$B$2:$B$5) -> NorthEast
A7: 6 | B7: Mississippi | C7: 3 | D7: =_xlfn.XLOOKUP(C7,REGION!$A$2:$A$5,REGION!$B$2:$B$5) -> South
A8: 7 | B8: Ney Jersey | C8: 2 | D8: =_xlfn.XLOOKUP(C8,REGION!$A$2:$A$5,REGION!$B$2:$B$5) -> MidAtlantic
A9: 8 | B9: New York | C9: 2 | D9: =_xlfn.XLOOKUP(C9,REGION!$A$2:$A$5,REGION!$B$2:$B$5) -> MidAtlantic
A10: 9 | B10: Texas | C10: 3 | D10: =_xlfn.XLOOKUP(C10,REGION!$A$2:$A$5,REGION!$B$2:$B$5) -> South
A11: 10 | B11: Washington | C11: 4 | D11: =_xlfn.XLOOKUP(C11,REGION!$A$2:$A$5,REGION!$B$2:$B$5) -> West

Sheet REL_CUSTOMER_STORE
A1: Customer_ID | B1: Store_ID
A2: 46 | B2: 1
A3: 47 | B3: 1
A4: 79 | B4: 1
A5: 46 | B5: 2
A6: 47 | B6: 2
A7: 79 | B7: 2
A8: 46 | B8: 3
A9: 47 | B9: 3
A10: 79 | B10: 3
A11: 35 | B11: 4
A12: 77 | B12: 4
A13: 87 | B13: 4
... A257: 80 | B257: 100
